cjeReportingTool/__init__.py
cjeReportingTool/cjeReportingTool.py
cjeReportingTool/main.py
cjeReportingTool-2.0.1.dist-info/LICENSE
cjeReportingTool-2.0.1.dist-info/METADATA
cjeReportingTool-2.0.1.dist-info/WHEEL
cjeReportingTool-2.0.1.dist-info/entry_points.txt
cjeReportingTool-2.0.1.dist-info/top_level.txt
cjeReportingTool-2.0.1.dist-info/RECORD
